iepy/__init__.py
iepy/addData.py
iepy/data.json
b23iepy-0.0.3.dist-info/LICENSE
b23iepy-0.0.3.dist-info/METADATA
b23iepy-0.0.3.dist-info/WHEEL
b23iepy-0.0.3.dist-info/top_level.txt
b23iepy-0.0.3.dist-info/RECORD
