Metadata-Version: 2.1
Name: b23iepy
Version: 0.0.3
Summary: Package for Hydrocarbon to Image conversion
Home-page: https://github.com/bertik23/iepy
Author: Bertik23
Author-email: bertikxxiii@gmail.com
License: UNKNOWN
Platform: UNKNOWN
Classifier: Programming Language :: Python :: 3
Classifier: License :: OSI Approved :: MIT License
Classifier: Operating System :: OS Independent
Requires-Python: >=3.8
